src/__init__.py
src/quickinit.py
quickinit-0.0.3.dist-info/LICENSE
quickinit-0.0.3.dist-info/METADATA
quickinit-0.0.3.dist-info/WHEEL
quickinit-0.0.3.dist-info/entry_points.txt
quickinit-0.0.3.dist-info/top_level.txt
quickinit-0.0.3.dist-info/RECORD
