Metadata-Version: 2.1
Name: quickinit
Version: 0.0.3
Summary: quickinit - quickly scaffold projects in Python, Golang, Web, Next.js and Rust.
Home-page: https://github.com/toine08/quickinit
Author: toto
Author-email: toto8@duck.com
Classifier: Programming Language :: Python :: 3
Classifier: License :: OSI Approved :: MIT License
Classifier: Operating System :: OS Independent
License-File: LICENSE
